trebellar/__init__.py
trebellar/assets/__init__.py
trebellar/assets/client.py
trebellar/assets/raw_client.py
trebellar/assets/types/__init__.py
trebellar/assets/types/add_single_assets_response.py
trebellar/assets/types/bulk_operations_assets_response.py
trebellar/assets/types/list_all_assets_request_from_asset_type.py
trebellar/assets/types/list_all_assets_response.py
trebellar/badge/__init__.py
trebellar/badge/client.py
trebellar/badge/raw_client.py
trebellar/badge/types/__init__.py
trebellar/badge/types/bulk_insert_badge_badge_response.py
trebellar/client.py
trebellar/core/__init__.py
trebellar/core/api_error.py
trebellar/core/client_wrapper.py
trebellar/core/datetime_utils.py
trebellar/core/file.py
trebellar/core/force_multipart.py
trebellar/core/http_client.py
trebellar/core/http_response.py
trebellar/core/http_sse/__init__.py
trebellar/core/http_sse/_api.py
trebellar/core/http_sse/_decoders.py
trebellar/core/http_sse/_exceptions.py
trebellar/core/http_sse/_models.py
trebellar/core/jsonable_encoder.py
trebellar/core/pydantic_utilities.py
trebellar/core/query_encoder.py
trebellar/core/remove_none_from_dict.py
trebellar/core/request_options.py
trebellar/core/serialization.py
trebellar/costs/__init__.py
trebellar/costs/client.py
trebellar/costs/raw_client.py
trebellar/environment.py
trebellar/errors/__init__.py
trebellar/errors/bad_request_error.py
trebellar/errors/internal_server_error.py
trebellar/errors/not_found_error.py
trebellar/errors/unprocessable_entity_error.py
trebellar/people/__init__.py
trebellar/people/client.py
trebellar/people/raw_client.py
trebellar/people_groups/__init__.py
trebellar/people_groups/client.py
trebellar/people_groups/raw_client.py
trebellar/people_groups/types/__init__.py
trebellar/people_groups/types/delete_people_group_people_groups_response.py
trebellar/people_groups/types/list_people_groups_people_groups_response.py
trebellar/py.typed
trebellar/types/__init__.py
trebellar/types/add_cost_line_batch_response.py
trebellar_api-1.2.0.dist-info/METADATA
trebellar_api-1.2.0.dist-info/WHEEL
trebellar_api-1.2.0.dist-info/RECORD
